<?xml version="1.0" encoding="UTF-8"?>
<MUP xmlns="http://www.mozarteum.at/ns/dme"
    xmlns:xsi="http://www.w3.org/2001/XMLSchema-instance">
    <mupHeader>
        <titleStmt>
            <title xml:lang="de">Digitale Edition der Briefe und Dokument der Familie Mozart</title>
            <title xml:lang="en">Digital Edition of Letters and Documents from the Mozart Family</title>
            <sponsor xml:id="ISM">
                    <orgName ref="https://d-nb.info/gnd/37019-8">Internationale Stiftung Mozarteum Salzburg</orgName>
                    <address>
                            <settlement ref="https://www.geonames.org/2766824">Salzburg</settlement>
                            <country>Austria</country>
                    </address>
            </sponsor>
            <funder xml:id="PHI">
                    <orgName>The Packard Humanities Institute</orgName>
                    <address>
                            <settlement ref="https://www.geonames.org/5368335">Los Altos</settlement>
                            <country>California, USA</country>
                    </address>
            </funder>
            <editor corresp="#DME" role="texteditor" xml:id="AM">
                    <persName>
                            <surname>Morgenstern</surname>
                            <forename>Anja</forename>
                            <note type="remarkResponsibility" xml:id="n_AM">
                                    text encoding, text editing
                            </note>
                    </persName>
            </editor>
            <editor corresp="#DME" role="techstaff" xml:id="FK">
                    <persName>
                            <surname>Kelnreiter</surname>
                            <forename>Franz</forename>
                            <note type="remarkResponsibility" xml:id="n_FK">
                                    technical supervisor, data modelling
                            </note>
                    </persName>
            </editor>
            <respStmt>
                    <orgName corresp="#ISM" xml:lang="de"
                    >Internationale Stiftung Mozarteum Salzburg
                            <orgName role="department" xml:id="DME">Wissenschaftliche Abteilung. Digitale Mozart-Edition
                                    <persName ref="https://d-nb.info/gnd/10403128X" role="head">Ulrich Leisinger</persName>
                                    <orgName role="project">Digitale Mozart-Edition</orgName>
                                    <ref type="web">https://dme.mozarteum.at</ref>
                            </orgName>
                    </orgName>
            </respStmt>
        </titleStmt>    
        <publStmt>
            <publisher><corpName sameas="#ISM"/></publisher>
            <date when="2013">2013-5</date>
            <availability>
                <useRestrict label="license">CC BY-NC-SA 4.0</useRestrict>
            </availability>
            <idno type="URLWeb">https://dme.mozarteum.at/DME/briefe/letter.php?mid=1108</idno>
        </publStmt>
        <srcDesc>
            <bibl type="source" subtype="short">A-Sm</bibl>
            <bibl type="source" subtype="RISM">A-Sm (Internationale Stiftung Mozarteum, Bibliotheca Mozartiana)</bibl>
        </srcDesc>
        <revisDesc>
            <change when="2021-08-19">file generation: <date>Thu Aug 19 14:55:58 2021</date></change>
        </revisDesc>
    </mupHeader>            
<text type="mobridoc" src="file:///T:/webpub_2019/BD_542.mup">
<letter bd="542"><HEADER id="1108">WOLFGANG AMADÉ MOZART AN LEOPOLD MOZART IN SALZBURG<lbr/>
MÜNCHEN, 24. NOVEMBER 1780</HEADER>
<pg n="1"/>
<ts>__________________</ts><tshtm>_____________________________________________________________</tshtm><tspdf>\hfill </tspdf><rend class="latin">Munic ce</rend> 24 <rend class="latin"><u>Nov:<h>bre</h></u></rend>&#160;<u>1780.</u><lbr type="forced"/>
<ts>______________</ts><tshtm>_____________</tshtm><rend class="latin">Mon trés cher Pére!</rend><lbr type="forced"/>
<lbr type="forced"/>
Ich habe das <rend class="latin">Paquet</rend> und ihren lezten brief von 20:<h>ten</h> richtigst erhalten &#8211;<lbr type="BD"/>&#160;<lbr/>
Herr schachtner beko<abbr type="topline" expand="mm">m</abbr>t für seine Bemühung 10 <rend class="latin">Duccat</rend>en &#8211; Ich hoffe Sie<lbr type="BD"/><lbr/>
werden unterdessen auch die <rend class="latin">Aria</rend> für H<abbr type="curve">:</abbr> schickaneder erhalten haben.<lbr/>
&#8211; der<lbr type="BD"/>&#160;<rend class="latin">Mad:<h>selle</h> Catherine</rend> Gilofsk&#255; <rend class="latin">de Urazowa</rend> bitte meinen unter<pc force="weak">=</pc><lbr/>thänigsten <rend class="latin">Re<lbr type="BD"/>spect</rend> zu vermelden &#8211; und in meinen Namen alles schöne<lbr/>
zu ihrem Namens<lbr type="BD"/>tage anzuwünschen, Besonders wünsche ich ihr, daß dies<lbr/>
das leztemal se&#255;e,<lbr type="BD"/> daß man ihr als <rend class="latin">Mad:<h>selle</h></rend> gratuliere &#8211; &#8211; <lbr type="forced"/>
<add_note schr_id="57010"><ts>_____________________________________</ts>Seinsheim</add_note>
was sie mir wegen graf <encr expand="sensheim">olnoulfa</encr> schreiben, ist schon lange geschehen &#8211;<lbr type="BD"/>&#160;<lbr/>
das hängt Ja alles so an einer kette; &#8211; ich habe schon einmal be&#255; ihm<lbr/>
<add_note schr_id="57010"><ts>_____________________________________________________</ts>Baumgarten</add_note>
zu<lbr type="BD"/> Mittage gespeist; 2 mal beÿm <u><encr expand="Baumgarten">Bmhagmrtln</encr></u> und 1. mal be&#255;m<lbr/>
<add_note schr_id="57010">Lerchenfeld<ts>_________________</ts>Baumgarten</add_note>
<u><encr expand="Lerchenfeld">Elrculn<lbr type="BD"/>iled</encr></u> &#8211; davon die <u><encr expand="Baum">Bmha</encr></u>&#160;<u>etc.</u> eine Tochter ist. &#8211; da ist kein<lbr/>
tag wo nicht<lbr type="BD"/> wenigstens Jemand von diesen leüten zum <rend class="latin">Ca<abbr type="topline" expand="nn">n</abbr>abich</rend> kö<abbr type="topline" expand="mm">m</abbr>t;<lbr/>
<add_note schr_id="57010"><ts>______________</ts>meiner<ts>_____</ts>opera</add_note>
&#8211; wegen<lbr type="BD"/>&#160;<u><encr expand="meiner opera">alfnlr splrm</encr></u> se&#255;en sie ausser Sorg, mein liebster vatter &#8211; <lbr/>
<add_note schr_id="57010"><ts>____________________________________________________________________</ts>Eine kleine Kabale</add_note>
Ich hoffe das<lbr type="BD"/> alles ganz gut gehen wird. &#8211; <u><encr expand="eine kleine">lfnl kefnl</encr>&#160;<rend class="latin"><encr expand="Cabale">Cmbmel</encr></rend></u><lbr/>
wird es wohl absetzen &#8211;<lbr type="BD"/> die aber vermuthlich sehr Comisch ausfallen<lbr/>
<add_note schr_id="57010"><ts>____________________________________________________</ts>Noblesse<ts>_______</ts>ansehnlichsten</add_note>
wird &#8211;. de<abbr type="topline" expand="nn">n</abbr> &#8211; ich habe unter<lbr type="BD"/> der <rend class="latin"><encr expand="Noblesse">Nsbelool</encr></rend> die <encr expand="ansehnlichsten">mnolunefcuotln</encr><lbr/>
<add_note schr_id="57010"><ts>_____</ts>vermöglichsten<ts>___________</ts>Häuser<ts>_____________</ts>ersten bei der</add_note>
und <encr expand="vermöglichsten häuser">vlras"efcuotln um"holr</encr> &#8211; und<lbr type="BD"/> die <encr expand="ersten Be&#255; der Musick">lrotln Bl&#255; dlr Ahofck</encr><lbr/>
<add_note schr_id="57010">Musik<ts>________________________________________________________________________________</ts>Cannabich</add_note>
sind alle für mich &#8211; Ich ka<abbr type="topline" expand="nn">n</abbr> ihnen nicht sagen<lbr type="BD"/> wie sehr <encr expand="Cannabich">Cmnnmbfcu</encr><lbr/>
<add_note schr_id="57010">mein<ts>___</ts>Freund<ts>__</ts>ist<ts>__________</ts>thätig<ts>____________</ts>wirksam</add_note>
<encr expand="mein freund ist">alfn irlhnd fot</encr>. &#8211; wie <u><encr expand="thätig">tum"tfg</encr></u> &#8211; <u><encr expand="wirksam">wfrkoma</encr></u> &#8211; mit<lbr type="BD"/> einem Worte,<lbr/>
<add_note schr_id="57010"><ts>_____________</ts>Laurer<ts>______________________________________________</ts>Jemanden Gutes</add_note>
er ist ein <u><encr expand="Lauerer">Lmhlrlr</encr></u> &#8211; we<abbr type="topline" expand="nn">n</abbr> es darauf ankö<abbr type="topline" expand="mm">m</abbr>t <encr expand="iemanden gutes">flamndln<lbr type="BD"/> ghtlo</encr><lbr/>
<add_note schr_id="57010">zu</add_note>
<encr expand="zu">zh</encr> tuhn. &#8211; wegen der geschichte vom Mara will ich sie ihnen <u>ganz</u><lbr type="BD"/><lbr/>
erzehlen &#8211; warum ich ihnen nie etwas davon schrieb, ist ursach, weil ich<lbr type="BD"/><lbr/>
mir dachte, wissen sie nichts davon, werden sie es schon hier selbst hören,<lbr type="BD"/><lbr/>
und wissen sie was, so ist es allzeit zeit ihnen die ganze wahrheit davon<lbr/>
zu<lbr type="BD"/> schreiben &#8211; de<abbr type="topline" expand="nn">n</abbr> vermuthlich wird man wohl was darzu gemacht<lbr/>
haben &#8211;<lbr type="BD"/> wenigstens hier in der stadt hat man sie auf gar viellerle&#255;<lbr/>
art erzehlt. &#8211; ich<lbr type="BD"/> ka<abbr type="topline" expand="nn">n</abbr> es aber an besten wissen, weil ich zugegen<lbr/>
war, und folglich be&#255; der<lbr type="BD"/> ganzen <rend class="latin">affaire</rend> ein zuseher und zuhörer war.<lbr/>
als die Erste <rend class="latin">Sinfonie</rend> vorbe&#255;<lbr type="BD"/> war, traff es <rend class="latin">Mad:<h>me</h> Mara</rend> zu singen &#8211; <lbr/>
da sah ich ihren h<abbr type="curve">:</abbr> Gemahl hinter ihr<lbr type="BD"/> mit einen <rend class="latin">violoncell</rend> in der hand<lbr/>
herschleichen &#8211; ich glaubte es wird eine<lbr type="BD"/> mit einen <rend class="latin">violoncell obligate aria</rend><lbr/>
se&#255;n &#8211; der alte Danzi &#8211; |: ein sehr guter<lbr type="BD"/>&#160;<rend class="latin">accompagneteur</rend> :| ist erster<lbr/>
<lbr/>
<add_seal type="owner">DOM=<lbr type="forced"/>MUSICK=VEREIN<lbr type="forced"/>U.<lbr type="forced"/>MOZARTEUM</add_seal>
<lbr/>
<add_seal type="owner">INTERNATIONALE<lbr type="forced"/>STIFTUNG:<lbr type="forced"/>„MOZARTEUM”<lbr type="forced"/>1881</add_seal>
<pg n="2"/>
violoncellist hier; auf einmal sagt der alte<lbr type="BD"/> toeski |: auch <rend class="latin">Director</rend> aber<lbr/>
in den <rend class="latin">Moment</rend> we<abbr type="topline" expand="nn">n</abbr> <rend class="latin">Ca<abbr type="topline" expand="nn">n</abbr>abich</rend> da ist, nichts zu befehlen hat :| zum <rend class="latin">Danzi</rend><lbr/>
|: <rend class="latin"><u>NB</u>:</rend> zu seinem schwiegersohn :| <u>steh er auf, und<lbr type="BD"/> laß er den <rend class="latin">Mara</rend><lbr/>
hersitzen</u> &#8211; als dies <rend class="latin">Ca<abbr type="topline" expand="nn">n</abbr>abich</rend> hört und sieht &#8211; schre&#255;t er;<lbr type="BD"/>&#160;<rend class="latin"><u>Danzi</u>,</rend><lbr/>
<u>bleiben sie sitzen &#8211; der Churfürst sieht gern we<abbr type="topline" expand="nn">n</abbr> seine leute <rend class="latin">accom<pc force="weak">=</pc><lbr/>pagn</rend>iren</u>. &#8211; darauf gieng die <rend class="latin">aria</rend> an &#8211; <rend class="latin">Giov Mara</rend> stunde wie<lbr/>
ein armer sünder<lbr type="BD"/> mit den <rend class="latin">Bassl</rend> in der hand hinter seiner frau &#8211; <lbr/>
als sie in den saal eintratten,<lbr type="BD"/> waren sie mir be&#255;de schon unerträglich<lbr/>
&#8211; de<abbr type="topline" expand="nn">n</abbr> so was freches hat man nicht<lbr type="BD"/> bald gesehen &#8211; sie werden<lbr/>
in der folge davon überzeugt se&#255;n. &#8211; die <rend class="latin">aria</rend><lbr type="BD"/> hatte einen 2:<h>ten</h><lbr/>
theil &#8211; <rend class="latin">Mad:<h>me</h> Mara</rend> fand es nicht für gut das <rend class="latin">orchestre</rend><lbr type="BD"/> vorher zu <rend class="latin">avisieren</rend>,<lbr/>
sondern gieng mit ihrer angebohrnen <rend class="latin">Air d'effronterie</rend><lbr type="BD"/> unter dem lezten<lbr/>
<rend class="latin">Ritornell</rend> herab um den hohen Herschaften ihr <rend class="latin">Compliment</rend><lbr type="BD"/> zu machen.<lbr/>
unterdessen fieng ihr Ma<abbr type="topline" expand="nn">n</abbr> mit dem <rend class="latin">Ca<abbr type="topline" expand="nn">n</abbr>abich</rend> an &#8211; alles ka<abbr type="topline" expand="nn">n</abbr><lbr type="BD"/> ich nicht<lbr/>
schreiben, es würde zu lang &#8211; mit einem Worte, er beschimpfte<lbr/>
das<lbr type="BD"/>&#160;<rend class="latin">orchestre</rend> &#8211; den <rend class="latin">Caractére</rend> des <rend class="latin">Ca<abbr type="topline" expand="nn">n</abbr>abichs</rend> &#8211; Natürlicher weise<lbr/>
war <rend class="latin">Ca<abbr type="topline" expand="nn">n</abbr>abich</rend><lbr type="BD"/> aufgebracht &#8211; kriegte ihn an Arm, und sagte:<lbr/>
hier ist der Platz nicht ihnen zu<lbr type="BD"/> antworten &#8211; <rend class="latin">Mara</rend> wollte noch reden,<lbr/>
er drohte ihn aber, we<abbr type="topline" expand="nn">n</abbr> er nicht<lbr type="BD"/> schwiege, <suppl hand="self" pos="supra">ihn</suppl> hinaus führen zu lassen.<lbr/>
&#8211; alles war über die <rend class="latin">impertinence</rend> des<lbr type="BD"/>&#160;<rend class="latin">Mara</rend> aufgebracht &#8211; <lbr/>
unterdessen war ein <rend class="latin">Concert</rend> von <rend class="latin">Ra<abbr type="topline" expand="mm">m</abbr></rend>; &#8211; da giengen<lbr type="BD"/> die 2<lbr/>
lieben Ehleute zum Graf <rend class="latin">Seeau</rend> klagen &#8211; sie fanden aber auch<lbr/>
da, wie<lbr type="BD"/> be&#255; allen leuten, daß sie unrecht hatten &#8211; Endlich begieng<lbr/>
<rend class="latin">Mad:<h>me</h> Mara</rend> die<lbr type="BD"/>&#160;<rend class="latin">Sottise</rend> selbst zum Churfürsten deswegen hinab<lbr/>
zu gehen &#8211; und ihr Ma<abbr type="topline" expand="nn">n</abbr><lbr type="BD"/> sagte unterdessen ganz stolz: <u>Meine frau<lbr/>
klagt itzt eben be&#255;m Churfürsten;<lbr type="BD"/> das wird den <rend class="latin">Ca<abbr type="topline" expand="nn">n</abbr>abich</rend> sein unglück<lbr/>
se&#255;n &#8211; es thut mir leid</u>. er wurde aber<lbr type="BD"/> ganz herrlich darüber aus<pc force="weak">=</pc><lbr/>gelacht. &#8211; der Churfürst antwortete auf die klage der<lbr type="BD"/>&#160;<rend class="latin">Mad.<h>me</h> Mara</rend>;<lbr/>
<u><rend class="latin">Madame</rend>; sie haben wie ein Engel gesungen, obwohl ihnen ihr<lbr type="BD"/> Man<lbr/>
nicht <rend class="latin">accompagniert</rend> hat</u>. und als sie ihre klage <rend class="latin">poussier</rend>en wollte, sagte<lbr type="BD"/><lbr/>
er; Ja, das geht mich nichts an, sondern graf <rend class="latin">Seau</rend>. &#8211; als sie sahen<lbr/>
daß da<lbr type="BD"/> nichts zu machen war, so giengen sie weiter &#8211; ob wohl sie noch 2 <rend class="latin">arien</rend><lbr/>
zu<lbr type="BD"/> singen hatte &#8211; das heist auf teütsch den Churfürsten <rend class="latin">affront</rend>iren &#8211; <lbr/>
<lbr/>
<add_seal type="owner">INTERNATIONALE<lbr type="forced"/>STIFTUNG:<lbr type="forced"/>„MOZARTEUM”<lbr type="forced"/>1881</add_seal>
<pg n="3"/>
und ich<lbr type="BD"/> weis gewis we<abbr type="topline" expand="nn">n</abbr> nicht der Erzherzog und vielle andere fremde da gewesen<lbr type="BD"/><lbr/>
wären, man würde ihnen ganz anders begegnet se&#255;n &#8211; aber auf diese art war<lbr type="BD"/><lbr/>
dem graf Seeau scheiß bange, schickte ihnen gleich Nach &#8211; und sie ka<abbr type="topline" expand="mm">m</abbr>en<lbr type="BD"/> wieder<lbr/>
zurück; &#8211; sie sang ihre 2 <rend class="latin">arien</rend> ohne von ihren Ma<abbr type="topline" expand="nn">n</abbr> <rend class="latin">accompag</rend>nirt zu<lbr type="BD"/> se&#255;n.<lbr/>
be&#255; der letzten &#8211; Ich glaube i<abbr type="topline" expand="mm">m</abbr>er daß es h<abbr type="curve">:</abbr>&#160;<rend class="latin">Mara</rend> mit fleiß gethan &#8211;<lbr type="BD"/>&#160;<lbr/>
giengen |: <rend class="latin">NB.</rend> nur in der abschrift wo <rend class="latin">Ca<abbr type="topline" expand="nn">n</abbr>abich</rend> spiellte :| 3 täckt ab &#8211; <lbr/>
als<lbr type="BD"/> dieses ka<abbr type="topline" expand="mm">m</abbr>, hielte <rend class="latin">Mara</rend> dem Ca<abbr type="topline" expand="nn">n</abbr>abich den Arm &#8211; dieser fande<lbr/>
sich gleich &#8211; schlug aber mit den Bogen auf das Pult, und schrie laut;<lbr/>
<u>hier ist<lbr type="BD"/> alles gefehlt</u> &#8211; wie die <rend class="latin">aria</rend> aus war; &#8211; <u>sagte er</u>: <u>h<abbr type="curve">:</abbr>&#160;<rend class="latin">Mara</rend></u>,<lbr/>
<u>ich will ihnen<lbr type="BD"/> einen Rath geben &#8211; lassen sie es ihnen gesagt se&#255;n,</u> &#8211; <lbr/>
<u>halten sie keinen<lbr type="BD"/>&#160;<rend class="latin">Directeur</rend> von einen <rend class="latin">Orchestre</rend> den Arm &#8211; de<abbr type="topline" expand="nn">n</abbr> sie kö<abbr type="topline" expand="nn">n</abbr>en<lbr/>
sich sonst i<abbr type="topline" expand="mm">m</abbr>er<lbr type="BD"/> auf ein halb duzend ohrfeigen rechnung machen</u> &#8211; <lbr type="forced"/>
<rend class="latin">Maras</rend> ton war aber nun schon ganz herabgesti<abbr type="topline" expand="mm">m</abbr>t &#8211; er bat um verzeihung,<lbr type="BD"/><lbr/>
entschuldigte sich aufs Beste. &#8211; das schändlichste be&#255; der ganzen <rend class="latin">affaire</rend> war,<lbr type="BD"/><lbr/>
daß <rend class="latin">Mara</rend> |: ein Elender <rend class="latin">violoncellist</rend>, wie alles hier sagt :| gar sich nicht be&#255;<lbr type="BD"/> hofe<lbr/>
hätte hören lassen, wenn nicht <rend class="latin">Ca<abbr type="topline" expand="nn">n</abbr>abich</rend> gewesen wäre, der sich darum<lbr type="BD"/> Mühe<lbr/>
gegeben hat &#8211; in der Ersten <rend class="latin">accademie</rend> da ich noch nicht hier war,<lbr type="BD"/> spiellte er<lbr/>
<rend class="latin">Concert</rend>, <rend class="latin">accompagnierte</rend> seiner frau, setzte sich, ohne weder dem<lbr type="BD"/>&#160;<rend class="latin">Danzi</rend> noch<lbr/>
Jemand was zu sagen, an <rend class="latin">Danzi</rend> seinen Platz &#8211; das liess man so<lbr type="BD"/><lbr/>
hin gehen. der Churfürst war mit seinem <rend class="latin">accompagement</rend> gar nicht zu<lbr type="BD"/><lbr/>
frieden. sagte: er sähe lieber daß seine leute <rend class="latin">accompag</rend>nirten &#8211; <rend class="latin">Ca<abbr type="topline" expand="nn">n</abbr>abich</rend><lbr type="BD"/><lbr/>
der das wuste, sagte es dem Grafen, bevor die <rend class="latin">accademie</rend> anfieng.<lbr/>
er kö<abbr type="topline" expand="nn">n</abbr>e<lbr type="BD"/> wohl auf der andern seite mitspiellen, aber <rend class="latin">Danzi</rend> Muß auch<lbr/>
spiellen; und als<lbr type="BD"/>&#160;<rend class="latin">Mara</rend> kam, sagte er es ihm &#8211; und doch &#8211; begieng<lbr/>
er die <rend class="latin">impertinence</rend>; &#8211;<lbr type="BD"/> we<abbr type="topline" expand="nn">n</abbr> sie sie ke<abbr type="topline" expand="nn">n</abbr>en sollten die 2 leute, man<lbr/>
sieht ihnen den stolz, grobheit,<lbr type="BD"/> und wahre <rend class="latin">Effronterie</rend> im Gesichte an.<lbr type="forced"/>
&#8211; Nun hoffe wird wohl meine schwester wieder gesund se&#255;n! &#8211; Ich bitte<lbr/>
sie,<lbr type="BD"/> schreiben Sie mir keinen so trauerigen Brief mehr &#8211; de<abbr type="topline" expand="nn">n</abbr> &#8211; ich<lbr/>
brauche der<lbr type="BD"/>malen ein heiteres Gemüth &#8211; leichten kopf &#8211; und lust zum<lbr/>
arbeiten &#8211; und<lbr type="BD"/> das hat man nicht we<abbr type="topline" expand="nn">n</abbr> man trauerig ist &#8211; Ich<lbr/>
weis, und fühl es Be&#255; Gott,<lbr type="BD"/> wie sehr sie Ruhige stunden verdienten!<lbr/>
allein &#8211; bin ich de<abbr type="topline" expand="nn">n</abbr> das hinder<lbr type="BD"/>nüss? &#8211; ich möchte es nicht se&#255;n, und<lbr/>
<add_note schr_id="57010"><ts>______________________________________________________________________________</ts>Zwek erreiche</add_note>
&#8211; leider bin ich es doch! &#8211; aber; &#8211; we<abbr type="topline" expand="nn">n</abbr><lbr type="BD"/> ich meinen <encr expand="Zweck ereiche">Zwlck lrlfcul</encr> &#8211; daß<lbr/>
<add_note schr_id="57010">ich<ts>______</ts>hier ansehnlich ankommen<ts>________________________</ts>Sie<ts>________</ts>den Augenblik</add_note>
<encr expand="Ich hier ansehnlich ankommen">Icu uflr mnolunefcu mnksaaln</encr> ka<abbr type="topline" expand="nn">n</abbr> &#8211;<lbr type="BD"/> so müssen <encr expand="sie den augenblick">ofl dln mhglnbefck</encr><lbr/>
<add_note schr_id="57010"><ts>__</ts>von Salzburg weg.<ts>___________________________________________________________________________</ts>meinen</add_note>
<encr expand="von salzburg weg">vsn omezbhrg wlg</encr>. &#8211; das geschieht nicht,<lbr type="BD"/> werden sie sagen &#8211; &#8211; an <encr expand="meinen">alfnln</encr><lbr/>
<lbr/>
<add_seal type="owner">DOM=<lbr type="forced"/>MUSICK=VEREIN<lbr type="forced"/>U.<lbr type="forced"/>MOZARTEUM</add_seal>
<pg n="4" type="wordsep"/><add_note schr_id="57010">Fleiß<ts>_________________</ts>Bemühung</add_note>
<encr expand="fleis">ielfo</encr> und <encr expand="Bemühung">Blmh"uhng</encr> wird wenigstens der<lbr type="BD"/> fehler nicht se&#255;n &#8211; <lbr type="forced"/>
sehen sie nur daß sie bald zu mir herauf ko<abbr type="topline" expand="mm">m</abbr>en &#8211; we<abbr type="topline" expand="nn">n</abbr> Nur der<lbr/>
<u><uu>E</uu>sel<lbr type="BD"/> welcher einen <uu>R</uu>ing <uu>z</uu>ereist, und durch die gewalt einen <uu>B</uu>ruch bekö<abbr type="topline" expand="mm">m</abbr>et</u>,<lbr/>
<u>daß<lbr type="BD"/>&#160;<uu>i</uu>ch ihn darüber <uu>sch</uu>eissen höre wie einen <rend class="latin">Castraten</rend> mit hörner, und mit<lbr type="BD"/><lbr/>
seinem langen <uu>o</uu>hr den <uu>f</uu>uchs=<tspdf>\newline</tspdf> schwanz streicht, nicht so</u> . . . . . . wäre.<lbr/>
wir kö<abbr type="topline" expand="nn">n</abbr>en alle Be&#255;sa<abbr type="topline" expand="mm">m</abbr>en wohnen. ich habe in meinen Ersten Zi<abbr type="topline" expand="mm">m</abbr>er eine<lbr type="BD"/><lbr/>
grosse <rend class="latin">Alcove</rend> wori<abbr type="topline" expand="nn">n</abbr>en zwe&#255; Better stehen &#8211; daß ist nun für Sie<lbr/>
und mich<lbr type="BD"/>&#160;<rend class="latin">charmant</rend>. Nun aber wegen meiner schwester wird kein ander<lbr/>
Mittel se&#255;n,<lbr type="BD"/> als &#8211; daß man einen ofen in das andere Zi<abbr type="topline" expand="mm">m</abbr>er setzen<lbr/>
lässt &#8211; das wird eine<lbr type="BD"/>&#160;<rend class="latin">affaire</rend> von ungefähr 4 bis 5 Gulden se&#255;n &#8211; <lbr/>
de<abbr type="topline" expand="nn">n</abbr>, Man möchte Einheitzen daß<lbr type="BD"/> der ofen sprengen sollte, und die<lbr/>
thüre hinein offen lassen &#8211; so würde es<lbr type="BD"/> doch nicht erträglich werden &#8211; <lbr/>
&#8211; de<abbr type="topline" expand="nn">n</abbr>, es hat eine gri<abbr type="topline" expand="mm">m</abbr>ige kälte dari<abbr type="topline" expand="nn">n</abbr>. &#8211;<lbr type="BD"/>&#160;<lbr type="forced"/>
fragen sie doch den <rend class="latin">Abate varesco</rend> ob man be&#255; dem Chor im 2:<h>ten</h> Ackt <u><rend class="latin">Placido</rend></u><lbr type="BD"/><lbr/>
<rend class="latin"><u>è il mar</u>. <u>Etc</u>.</rend> nachde<abbr type="topline" expand="mm">m</abbr> nach der Ersten strophe der <rend class="latin">Elletra</rend> der Chor<lbr/>
wieder<lbr type="BD"/>hollet worden, nicht aufhören könte? &#8211; wenigstens nach der<lbr/>
zwe&#255;ten &#8211; es<lbr type="BD"/> wird doch gar zu lang! &#8211; künftigen Postwagen hoffe<lbr/>
das <rend class="latin">Recitativ</rend> und <rend class="latin">Aria</rend><lbr type="BD"/> für h<abbr type="curve">:</abbr> Raaf richtig zu erhalten.<lbr type="forced"/>
ich bin nun zwe&#255; täge schon wegen meinem Chartar zu hause geblieben &#8211;<lbr type="BD"/>&#160;<lbr/>
und &#8211; zum glück daß ich nicht viell <rend class="latin">appetit</rend> hatte &#8211; de<abbr type="topline" expand="nn">n</abbr> in die länge<lbr/>
wäre es<lbr type="BD"/> mir ungelegen für das Essen zu zahlen &#8211; ich habe aber<lbr/>
dem grafen ein Billet<lbr type="BD"/> darüber geschrieben &#8211; er ließ mir sagen, er<lbr/>
wird schon mit mir darüber<lbr type="BD"/> sprechen &#8211; be&#255; gott! &#8211; ich zahle keinen<lbr/>
kreützer! er muß sich Ja in die Seele<lbr type="BD"/> schä<abbr type="topline" expand="mm">m</abbr>en &#8211; Nun <rend class="latin">adieu</rend>;<lbr/>
Machen sie doch allen guten freundn und freundin<lbr type="BD"/> meine Empfehlung<lbr/>
von hier von allen &#8211; 1000 <rend class="latin">Compli</rend>menten. ich küsse ihnen<lbr type="BD"/> 1000mahl<lbr/>
die hände und Meine schwester umarme ich aus ganzen herzen &#8211;<lbr type="BD"/>&#160;<lbr/>
und hoffe alles gute von ihrer gesundheit, und bin Ewig<lbr type="forced"/>
<lbr type="forced"/>
<add_note type="inline" schr_id="57010">Die drei Zeilen oben, die angestrichen sind,</add_note><lbr/>
<add_note type="inline" schr_id="57010">sind Chiffresprache und bedeuten blos:</add_note><ts>__________________</ts><tspdf>\hfill </tspdf>gehorsamster Sohn<lbr type="forced"/>
<add_note type="inline" schr_id="57010"><ts>_____________</ts>Erzbischof.</add_note><ts>__________</ts><tshtm>______________________________</tshtm><tspdf>\hfill </tspdf>Wolfgang Amadè Mozart <abbr expand="manu propria">mp</abbr><lbr type="forced"/>
<lbr/>
<add_seal type="owner">DOM=<lbr type="forced"/>MUSICK=VEREIN<lbr type="forced"/>U.<lbr type="forced"/>MOZARTEUM</add_seal>
<lbr/>
<add_seal type="owner">INTERNATIONALE<lbr type="forced"/>STIFTUNG:<lbr type="forced"/>„MOZARTEUM”<lbr type="forced"/>1881</add_seal>
</letter>
</text>
</MUP>